pycounts_ng24/.DS_Store
pycounts_ng24/.mypy_cache/.gitignore
pycounts_ng24/.mypy_cache/3.9/@plugins_snapshot.json
pycounts_ng24/.mypy_cache/3.9/_ast.data.json
pycounts_ng24/.mypy_cache/3.9/_ast.meta.json
pycounts_ng24/.mypy_cache/3.9/_codecs.data.json
pycounts_ng24/.mypy_cache/3.9/_codecs.meta.json
pycounts_ng24/.mypy_cache/3.9/_collections_abc.data.json
pycounts_ng24/.mypy_cache/3.9/_collections_abc.meta.json
pycounts_ng24/.mypy_cache/3.9/_typeshed/__init__.data.json
pycounts_ng24/.mypy_cache/3.9/_typeshed/__init__.meta.json
pycounts_ng24/.mypy_cache/3.9/abc.data.json
pycounts_ng24/.mypy_cache/3.9/abc.meta.json
pycounts_ng24/.mypy_cache/3.9/builtins.data.json
pycounts_ng24/.mypy_cache/3.9/builtins.meta.json
pycounts_ng24/.mypy_cache/3.9/codecs.data.json
pycounts_ng24/.mypy_cache/3.9/codecs.meta.json
pycounts_ng24/.mypy_cache/3.9/collections/__init__.data.json
pycounts_ng24/.mypy_cache/3.9/collections/__init__.meta.json
pycounts_ng24/.mypy_cache/3.9/collections/abc.data.json
pycounts_ng24/.mypy_cache/3.9/collections/abc.meta.json
pycounts_ng24/.mypy_cache/3.9/contextlib.data.json
pycounts_ng24/.mypy_cache/3.9/contextlib.meta.json
pycounts_ng24/.mypy_cache/3.9/dataclasses.data.json
pycounts_ng24/.mypy_cache/3.9/dataclasses.meta.json
pycounts_ng24/.mypy_cache/3.9/email/__init__.data.json
pycounts_ng24/.mypy_cache/3.9/email/__init__.meta.json
pycounts_ng24/.mypy_cache/3.9/email/charset.data.json
pycounts_ng24/.mypy_cache/3.9/email/charset.meta.json
pycounts_ng24/.mypy_cache/3.9/email/contentmanager.data.json
pycounts_ng24/.mypy_cache/3.9/email/contentmanager.meta.json
pycounts_ng24/.mypy_cache/3.9/email/errors.data.json
pycounts_ng24/.mypy_cache/3.9/email/errors.meta.json
pycounts_ng24/.mypy_cache/3.9/email/header.data.json
pycounts_ng24/.mypy_cache/3.9/email/header.meta.json
pycounts_ng24/.mypy_cache/3.9/email/message.data.json
pycounts_ng24/.mypy_cache/3.9/email/message.meta.json
pycounts_ng24/.mypy_cache/3.9/email/policy.data.json
pycounts_ng24-0.1.0.dist-info/LICENSE
pycounts_ng24-0.1.0.dist-info/METADATA
pycounts_ng24-0.1.0.dist-info/WHEEL
pycounts_ng24-0.1.0.dist-info/RECORD
